obal/__init__.py
obal/__main__.py
obal/data/__init__.py
obal/data/ansible.cfg
obal/data/module_utils/__init__.py
obal/data/module_utils/copr.py
obal/data/module_utils/koji_wrapper.py
obal/data/module_utils/obal.py
obal/data/module_utils/tito_wrapper.py
obal/data/modules/changelog.py
obal/data/modules/check_koji_build.py
obal/data/modules/copr_build.py
obal/data/modules/copr_build_info.py
obal/data/modules/copr_chroot.py
obal/data/modules/copr_fork.py
obal/data/modules/copr_project.py
obal/data/modules/koji_build.py
obal/data/modules/koji_find_tags.py
obal/data/modules/koji_tag_package.py
obal/data/modules/koji_verify_tag.py
obal/data/modules/package_whitelist_check.py
obal/data/modules/repoclosure.py
obal/data/modules/rpm_nevr.py
obal/data/modules/rpm_nvr.py
obal/data/modules/rpmspec_changelog_check.py
obal/data/modules/srpm.py
obal/data/modules/tito_build.py
obal/data/modules/tito_release.py
obal/data/playbooks/add/add.yaml
obal/data/playbooks/add/metadata.obal.yaml
obal/data/playbooks/bump-release/bump-release.yaml
obal/data/playbooks/bump-release/metadata.obal.yaml
obal/data/playbooks/changelog/changelog.yaml
obal/data/playbooks/changelog/metadata.obal.yaml
obal/data/playbooks/check/check.yaml
obal/data/playbooks/check/metadata.obal.yaml
obal/data/playbooks/cleanup-copr/cleanup-copr.yaml
obal/data/playbooks/cleanup-copr/metadata.obal.yaml
obal/data/playbooks/copr-project/copr-project.yaml
obal/data/playbooks/copr-project/metadata.obal.yaml
obal/data/playbooks/lint/lint.yaml
obal/data/playbooks/lint/metadata.obal.yaml
obal/data/playbooks/mock/metadata.obal.yaml
obal/data/playbooks/mock/mock.yaml
obal/data/playbooks/nightly/metadata.obal.yaml
obal/data/playbooks/nightly/nightly.yaml
obal/data/playbooks/release/metadata.obal.yaml
obal/data/playbooks/release/release.yaml
obal/data/playbooks/repoclosure/metadata.obal.yaml
obal/data/playbooks/repoclosure/repoclosure.yaml
obal/data/playbooks/scratch/metadata.obal.yaml
obal/data/playbooks/scratch/scratch.yaml
obal-0.13.0.dist-info/licenses/LICENSE
obal-0.13.0.dist-info/METADATA
obal-0.13.0.dist-info/WHEEL
obal-0.13.0.dist-info/entry_points.txt
obal-0.13.0.dist-info/top_level.txt
obal-0.13.0.dist-info/RECORD
