Metadata-Version: 2.4
Name: obal
Version: 0.13.0
Summary: packaging wrapper using ansible
Home-page: https://github.com/theforeman/obal
Author: The Foreman Project
Author-email: foreman-dev@googlegroups.com
Keywords: ansible foreman packaging koji brew mock
Classifier: Development Status :: 3 - Alpha
Classifier: Intended Audience :: Developers
Classifier: Topic :: Software Development :: Build Tools
Classifier: License :: OSI Approved :: GNU General Public License v2 (GPLv2)
Classifier: Programming Language :: Python :: 3
Classifier: Programming Language :: Python :: 3.9
Classifier: Programming Language :: Python :: 3.10
Classifier: Programming Language :: Python :: 3.11
Classifier: Programming Language :: Python :: 3.12
Classifier: Programming Language :: Python :: 3.13
License-File: LICENSE
Requires-Dist: obsah>=0.0.3
Provides-Extra: argcomplete
Requires-Dist: argcomplete; extra == "argcomplete"
Dynamic: author
Dynamic: author-email
Dynamic: classifier
Dynamic: description
Dynamic: description-content-type
Dynamic: home-page
Dynamic: keywords
Dynamic: license-file
Dynamic: provides-extra
Dynamic: requires-dist
Dynamic: summary
